Metadata-Version: 2.1
Name: chempath
Version: 0.0.1
Summary: Chemical Database.
Home-page: https://github.com/clumsykun/chempath
Author: Zhao Kunwang
Author-email: clumsykundev@gmail.com
License: UNKNOWN
Platform: UNKNOWN
License-File: LICENSE
